mcp_email_server/__init__.py
mcp_email_server/app.py
mcp_email_server/cli.py
mcp_email_server/config.py
mcp_email_server/log.py
mcp_email_server/ui.py
mcp_email_server/emails/__init__.py
mcp_email_server/emails/classic.py
mcp_email_server/emails/dispatcher.py
mcp_email_server/emails/models.py
mcp_email_server/emails/provider/__init__.py
mcp_email_server/tools/__init__.py
mcp_email_server/tools/claude_desktop_config.json
mcp_email_server/tools/installer.py
mcp_email_server_fastmcp-0.0.2.dist-info/METADATA
mcp_email_server_fastmcp-0.0.2.dist-info/WHEEL
mcp_email_server_fastmcp-0.0.2.dist-info/entry_points.txt
mcp_email_server_fastmcp-0.0.2.dist-info/licenses/LICENSE
mcp_email_server_fastmcp-0.0.2.dist-info/RECORD
